quantum_language_optimizer/__init__.py
quantum_language_optimizer/core/__init__.py
quantum_language_optimizer/core/quantum_circuit.py
quantum_language_optimizer/core/quantum_rnn.py
quantum_language_optimizer/core/utils.py
quantum_language_optimizer/models/__init__.py
quantum_language_optimizer/models/base_model.py
quantum_language_optimizer/models/gpt_quantum.py
quantum_language_optimizer/tests/__init__.py
quantum_language_optimizer/tests/test_gpt_quantum.py
quantum_language_optimizer/tests/test_quantum_circuit.py
quantum_language_optimizer/tests/test_quantum_rnn.py
quantum_language_optimizer-0.1.0.dist-info/METADATA
quantum_language_optimizer-0.1.0.dist-info/WHEEL
quantum_language_optimizer-0.1.0.dist-info/entry_points.txt
quantum_language_optimizer-0.1.0.dist-info/top_level.txt
quantum_language_optimizer-0.1.0.dist-info/RECORD
