Metadata-Version: 2.1
Name: quantum-language-optimizer
Version: 0.1.0
Summary: A PyPI plugin to optimize large language models using Quantum Neural Networks
Home-page: https://github.com/yourusername/quantum_language_optimizer
Author: C.C.K Leon
Author-email: ckchau1@asu.edu
Classifier: Programming Language :: Python :: 3
Classifier: License :: OSI Approved :: MIT License
Classifier: Operating System :: OS Independent
Requires-Python: >=3.6
Requires-Dist: qiskit>=0.29.0
Requires-Dist: numpy>=1.19.2
Requires-Dist: torch>=1.7.0
